dcx_pd/__init__.py
dcx_pd/__main__.py
dcx_pd/_base.py
dcx_pd/_version.py
dcx_pd/models.py
dcx_pd/types.py
dcx_pd-0.0.4.dist-info/licenses/LICENSE
dcx_pd-0.0.4.dist-info/METADATA
dcx_pd-0.0.4.dist-info/WHEEL
dcx_pd-0.0.4.dist-info/entry_points.txt
dcx_pd-0.0.4.dist-info/top_level.txt
dcx_pd-0.0.4.dist-info/RECORD
