Metadata-Version: 2.4
Name: dcx-pd
Version: 0.0.4
Summary: Discord Chat Exporter (by Tyrrrz) json output parser to typed Pydantic V2 objects (no affiliation with Discord nor Tyrrrz)
Home-page: https://github.com/anamoyee/dcx-pd
Author: anamoyee
License: GPL-3.0 license
Project-URL: Source, https://github.com/anamoyee/dcx-pd
Classifier: Development Status :: 3 - Alpha
Classifier: Intended Audience :: Developers
Classifier: Programming Language :: Python :: 3.13
Classifier: Programming Language :: Python :: 3 :: Only
Classifier: Typing :: Typed
Classifier: Topic :: Utilities
Classifier: Operating System :: POSIX
Classifier: Operating System :: POSIX :: Linux
Classifier: Operating System :: MacOS
Classifier: Operating System :: Microsoft :: Windows
Classifier: Operating System :: Microsoft :: MS-DOS
Requires-Python: >=3.13
License-File: LICENSE
Requires-Dist: pydantic>=2.10.6
Requires-Dist: tcrutils>=13.1.23
Requires-Dist: rich>=14.0.0
Requires-Dist: arguably>=1.3.0
Requires-Dist: psutil>=7.0.0
Dynamic: author
Dynamic: classifier
Dynamic: description
Dynamic: description-content-type
Dynamic: home-page
Dynamic: license
Dynamic: license-file
Dynamic: project-url
Dynamic: requires-dist
Dynamic: requires-python
Dynamic: summary
